pubsub.py
of_pubsub-0.3.dist-info/DESCRIPTION.rst
of_pubsub-0.3.dist-info/METADATA
of_pubsub-0.3.dist-info/RECORD
of_pubsub-0.3.dist-info/WHEEL
of_pubsub-0.3.dist-info/metadata.json
of_pubsub-0.3.dist-info/top_level.txt
